CHANGES.rst
LICENSE
MANIFEST.in
README.rst
bootstrap.py
setup.py
src/aja/__init__.py
src/aja/utils.py
src/aja.egg-info/PKG-INFO
src/aja.egg-info/SOURCES.txt
src/aja.egg-info/dependency_links.txt
src/aja.egg-info/entry_points.txt
src/aja.egg-info/not-zip-safe
src/aja.egg-info/requires.txt
src/aja.egg-info/top_level.txt
src/aja/tasks/__init__.py
src/aja/tests/__init__.py
src/aja/tests/test_utils.py