Metadata-Version: 1.1
Name: aja
Version: 0.9.2
Summary: Buildout-based deployment made safe and easy
Home-page: https://github.com/pingviini/aja
Author: Jukka Ojaniemi
Author-email: jukka.ojaniemi@gmail.com
License: GPL
Keywords: deploy buildout
Platform: UNKNOWN
Classifier: Programming Language :: Python
Classifier: Programming Language :: Python :: 2.7
